LICENSE
README.rst
setup.py
SQLExecX.egg-info/PKG-INFO
SQLExecX.egg-info/SOURCES.txt
SQLExecX.egg-info/dependency_links.txt
SQLExecX.egg-info/not-zip-safe
SQLExecX.egg-info/requires.txt
SQLExecX.egg-info/top_level.txt
sqlexecx/__init__.py
sqlexecx/constant.py
sqlexecx/dialect.py
sqlexecx/exec.py
sqlexecx/loader.py
sqlexecx/log_support.py
sqlexecx/page_exec.py
sqlexecx/sql_exec.py
sqlexecx/sql_support.py
sqlexecx/table_exec.py
sqlexecx/table_limit_exec.py
sqlexecx/table_order_by.py
sqlexecx/table_page_exec.py
sqlexecx/table_support.py
sqlexecx/utils.py
test/test.py