Metadata-Version: 2.1
Name: SQLExecX
Version: 2.1.7
Summary: A easy, fast sql executor for Python. Supported MySQL, PostgreSQL, SQLite etc.
Home-page: https://gitee.com/summry/sqlexecx
Author: summy
Author-email: xiazhongbiao@126.com
License: UNKNOWN
Keywords: SQL,MySQL,PostgreSQL,SQLite,Database,Python,RDB
Platform: UNKNOWN
Requires-Python: >=3.6
License-File: LICENSE
